http_pyserver-0.1.4.4.dist-info/licenses/LICENSE
server/__init__.py
server/cache.py
server/render.py
server/request.py
server/response.py
server/response_codes.py
server/response_messages.py
server/routes.py
server/server.py
server/sessions.py
server/template.py
http_pyserver-0.1.4.4.dist-info/METADATA
http_pyserver-0.1.4.4.dist-info/WHEEL
http_pyserver-0.1.4.4.dist-info/top_level.txt
http_pyserver-0.1.4.4.dist-info/RECORD
