Metadata-Version: 2.4
Name: HTTP-PyServer
Version: 0.1.4.4
Summary: Simple way to make complex HTTP servers with python
Author-email: Alex-Jando <alexjando2007@outlook.com>
Project-URL: Homepage, https://github.com/Alex-Jando/HTTP-PyServer
Project-URL: Bug Tracker, https://github.com/Alex-Jando/HTTP-PyServer/issues
Classifier: Programming Language :: Python :: 3
Classifier: License :: OSI Approved :: MIT License
Classifier: Operating System :: OS Independent
Requires-Python: >=3.7
License-File: LICENSE
Dynamic: license-file
